MANIFEST.in
setup.cfg
setup.py
./Aperture.py
./CCD.py
./Camera.py
./Cartographer.py
./Catalogs.py
./Cosmics.py
./Focus.py
./Intrapixel.py
./Jitter.py
./Lightcurve.py
./Noise.py
./Observation.py
./PSF.py
./Stamper.py
./__init__.py
./defaults.py
./relations.py
./settings.py
./cosmical_realistic/__init__.py
./data/keplerTCE_DR24.txt
./data/rotation_McQuillan.txt
./debug/__init__.py
./documentation/__init__.py
./documentation/input.py
./relations/enclosedfractionofflux.txt
./relations/fluxes.txt
./relations/optimalnumberofpixels.txt
SPyFFI.egg-info/PKG-INFO
SPyFFI.egg-info/SOURCES.txt
SPyFFI.egg-info/dependency_links.txt
SPyFFI.egg-info/requires.txt
SPyFFI.egg-info/top_level.txt
cosmical_realistic/_cosmical.c
cosmical_realistic/cosmical.c
cosmical_realistic/cosmical.h
cosmical_realistic/fmemopen.c
cosmical_realistic/fmemopen.h
cosmical_realistic/seed_tw_ran.c
cosmical_realistic/seed_tw_ran.h
cosmical_realistic/st_dat.h
cosmical_realistic/twister.c
cosmical_realistic/twister.h